CHANGELOG.txt
INSTALL.txt
LICENSE.txt
README.txt
openTMMpreprint.pdf
setup.py
openTMM/__init__.py
openTMM.egg-info/PKG-INFO
openTMM.egg-info/SOURCES.txt
openTMM.egg-info/dependency_links.txt
openTMM.egg-info/not-zip-safe
openTMM.egg-info/requires.txt
openTMM.egg-info/top_level.txt
openTMM/mods/Makefile
openTMM/mods/__init__.py
openTMM/mods/boundary.py
openTMM/mods/fortran_utils.f90
openTMM/mods/layer.py