Metadata-Version: 1.0
Name: openTMM
Version: 0.1.0
Summary: Electrodynamic S-matrix Code
Home-page: http://mesoscopic.mines.edu/mediawiki/index.php/Free_Python_codes
Author: Alex J. Yuffa
Author-email: ayuffa@gmail.com
License: The MIT License
Platform: Linux
Platform: Unix
Platform: Mac OS X
Platform: Windows
Classifier: Development Status :: 4 - Beta
Classifier: Environment :: Console
Classifier: Intended Audience :: Developers
Classifier: Intended Audience :: Science/Research
Classifier: License :: OSI Approved :: MIT License
Classifier: Natural Language :: English
Classifier: Operating System :: POSIX :: Linux
Classifier: Operating System :: Unix
Classifier: Operating System :: MacOS :: MacOS X
Classifier: Operating System :: Microsoft :: Windows
Classifier: Programming Language :: Python :: 2.5
Classifier: Programming Language :: Python :: 2.6
Classifier: Programming Language :: Python :: 2.7
Classifier: Programming Language :: Fortran
Classifier: Topic :: Scientific/Engineering :: Physics
Classifier: Topic :: Scientific/Engineering :: Atmospheric Science
